{"rankings":{"comred":1,"hoared":1,"coohaw":0,"sposan":1,"clagre":1,"wesgre":1,"whtswi":0,"rewbla":0,"tribla":1,"rucspa":1,"wooduc":0,"chukar":1,"baispa":1,"henspa":0,"lecspa":1,"seaspa":1,"graspa":0,"bktspa":1,"norpin":1,"amewig":1,"norsho":1,"cintea":1,"buwtea":0,"motduc":1,"mallar":0,"ambduc":0,"gadwal":1,"anhing":0,"amepip":1,"sprpip":1,"chwwid":1,"whip-p1":0,"wesjay":1,"flsjay":0,"mexjay4":0,"goleag":1,"bkchum":1,"rthhum":0,"greegr":0,"grbher3":0,"olispa":1,"sagspa":1,"burowl":1,"verdin":1,"lessca":1,"redhea":1,"rinduc":1,"gresca":1,"blctit4":1,"tuftit":0,"oaktit":1,"juntit1":1,"britit":0,"uplsan":0,"cedwax":0,"bohwax":1,"rufgro":1,"amebit":0,"marmur":1,"categr":1,"buffle":1,"comgol":1,"bargol":1,"rethaw":0,"rolhaw":1,"reshaw":0,"gryhaw2":0,"brwhaw":0,"ferhaw":1,"swahaw":1,"grnher":0,"larbun":1,"laplon":1,"chclon":1,"smilon":1,"dunlin":1,"wessan":1,"leasan":1,"semsan":1,"calqua":1,"gamqua":1,"scaqua":1,"annhum":1,"coshum":0,"nobtyr":0,"cacwre":1,"crecar1":1,"canwar":0,"wlswar":1,"refwar":0,"norcar":0,"pyrrhu":1,"turvul":0,"veery":0,"herthr":0,"gycthr":1,"swathr":1,"canwre":0,"saggro":0,"piggui":1,"brncre":0,"chiswi":0,"vauswi":0,"wrenti":1,"mouplo":1,"semplo":1,"killde":0,"blkter":1,"larspa":1,"lesnig":1,"comnig":1,"bongul":1,"amedip":0,"norhar":0,"marwre":0,"sedwre":0,"lotduc":1,"evegro":1,"yebcuc":0,"bkbcuc":0,"mancuc":0,"norfli":1,"gilfli":1,"norbob":0,"rocpig":0,"incdov":1,"cogdov":1,"olsfly":1,"wewpew":1,"eawpew":0,"blkvul":1,"amecro":0,"norcro":1,"comrav":0,"chirav":1,"fiscro":0,"blujay":0,"stejay":1,"grnjay":1,"truswa":1,"tunswa":1,"mutswa":0,"brbhum":1,"blkswi":0,"monqua":0,"blugrs":0,"bbwduc":1,"fuwduc":1,"boboli":0,"pilwoo":0,"grycat":0,"libher":1,"redegr":0,"snoegr":0,"triher":0,"swtkit":0,"whtkit":0,"aldfly":0,"pasfly":1,"yebfly":1,"hamfly":1,"leafly":0,"dusfly":0,"corfly":1,"wilfly":0,"acafly":0,"gryfly":1,"horlar":0,"whiibi":1,"rusbla":1,"brebla":1,"merlin":1,"prafal":1,"gyrfal":1,"amekes":0,"wilsni1":1,"comloo":1,"pacloo":1,"retloo":1,"gubter1":0,"greroa":1,"kenwar":0,"mouwar":0,"macwar":1,"comyel":0,"whthaw":0,"nopowl":0,"pinjay":1,"blkoys":1,"ameoys":0,"casfin":1,"houfin":0,"purfin":0,"baleag":0,"woewar1":0,"bknsti":0,"barswa":0,"harduc":1,"caster1":0,"woothr":0,"yebcha":0,"bulori":1,"hooori":0,"balori":0,"scoori":1,"orcori":0,"miskit":1,"leabit":0,"varthr":1,"slcjun":1,"wilpta":1,"rocpta1":1,"logshr":1,"hergul":0,"calgul":1,"mewgul":1,"ribgul":0,"glwgul":1,"glagul":1,"gbbgul":0,"wesgul":0,"whtdov":1,"laugul":1,"fragul":1,"swawar":0,"margod":1,"hoomer":0,"redcro":1,"whwcro":1,"belkin1":0,"wesowl1":0,"gofwoo":1,"rebwoo":0,"rehwoo":0,"acowoo":1,"lewwoo":1,"gilwoo":1,"whwsco":1,"wiltur":0,"swaspa":0,"linspa":1,"sonspa":0,"abetow":1,"caltow":1,"cantow":1,"commer":0,"rebmer":1,"normoc":0,"bawwar":0,"brocow":1,"bnhcow":0,"norgan":0,"towsol":1,"woosto":0,"astfly":1,"grcfly":0,"ducfly":0,"bncfly":1,"paired":0,"subfly":0,"monpar":0,"clanut":0,"lobcur":1,"ycnher":0,"bcnher":0,"compau":0,"conwar":1,"mouqua":1,"sagthr":1,"orcwar":1,"lucwar":0,"tenwar":1,"naswar":1,"virwar":1,"rudduc":1,"osprey":0,"hrshaw":1,"louwat":0,"norwat":1,"houspa":0,"eutspa":0,"savspa":0,"foxspa":1,"lazbun":0,"blugrb1":1,"paibun":1,"indbun":0,"varbun":0,"batpig1":0,"whcpig2":1,"amwpel":1,"brnpel":0,"grypar":1,"gryjay":1,"cavswa":1,"cliswa":0,"bacspa":0,"ruwspa":0,"casspa":1,"oliwar":0,"phaino":1,"doccor":0,"neocor":0,"compoo":1,"renpha":1,"wilpha":1,"rinphe":0,"robgro":0,"bkhgro":1,"arcwar":1,"bkbmag1":1,"yebmag":1,"whhwoo":1,"attwoo1":1,"nutwoo":1,"dowwoo":0,"labwoo":1,"haiwoo":0,"pingro":1,"gnttow":1,"eastow":0,"spotow":1,"heptan":1,"westan":1,"scatan":0,"sumtan":1,"grekis":1,"rosspo1":1,"whfibi":0,"gloibi":0,"amgplo":1,"horgre":1,"rengre":1,"eargre":1,"pibgre":0,"bkcchi":0,"carchi":0,"mouchi":1,"borchi2":1,"chbchi":1,"buggna":0,"bktgna":1,"vesspa":0,"purmar":0,"prowar":1,"bushti":1,"verfly":1,"botgra":1,"grtgra":1,"comgra":0,"ameavo":1,"ruckin":1,"gockin":1,"mcclon":1,"banswa":0,"bklkit":1,"blkski":0,"rocwre":1,"blkpho":1,"easpho":0,"saypho":1,"amewoo":0,"ovenbi1":0,"calhum":1,"brthum":1,"rufhum":1,"allhum":0,"norpar":0,"btbwar":0,"babwar":1,"cerwar":0,"gchwar":0,"hoowar":0,"yerwar":1,"prawar":0,"yetwar":0,"bkbwar":0,"grawar":1,"magwar":0,"btywar":1,"herwar":1,"palwar":1,"chswar":0,"yelwar":0,"pinwar":0,"amered":0,"bkpwar":1,"camwar":1,"towwar":1,"btnwar":0,"moublu":1,"wesblu":0,"easblu":0,"rebnut":0,"whbnut":0,"bnhnut":1,"pygnut":0,"rensap":0,"rebsap":1,"wilsap":1,"yebsap":0,"lawgol":0,"pinsis":1,"lesgol":1,"amegfi":0,"dickci":0,"amtspa":1,"bkcspa":1,"brespa":1,"clcspa":1,"chispa":0,"fiespa":0,"nrwswa":0,"lotjae":1,"parjae":1,"forter":0,"comter":0,"arcter":1,"leater1":0,"eucdov":0,"brdowl":0,"easmea":0,"wesmea":1,"eursta":0,"nohowl":1,"treswa":0,"vigswa":1,"bewwre":1,"carwre":0,"benthr":0,"crithr":0,"cubthr":1,"lecthr":1,"lobthr":1,"calthr":1,"brnthr":0,"lesyel":1,"greyel":1,"willet1":0,"solsan":1,"houwre":0,"winwre":0,"amerob":0,"grpchi":1,"lepchi":0,"shtgro":1,"coukin":1,"thbkin":0,"grykin":0,"sctfly":1,"easkin":0,"weskin":1,"caskin":1,"gowwar":0,"buwwar":0,"bkwvir":0,"bkcvir1":0,"belvir":1,"yetvir":0,"warvir":0,"whevir":0,"hutvir":1,"reevir":0,"phivir":1,"gryvir":1,"yehbla":1,"whwdov":1,"moudov":0,"whtspa":1,"gocspa":1,"whcspa":1},"focal":["whbnut","haiwoo","mallar","whtspa","gockin","brncre","ribgul","ambduc","balori","woothr","norhar","comgol","hergul","hoomer","commer","wiltur","swaspa","amekes","treswa","scatan","baleag","wilfly","rinduc","gadwal","herthr","purfin","lessca","rebnut","veery","yebsap","boboli","buffle","doccor","horgre","ovenbi1","buwwar","nswowl","comloo","rebmer","amewig","wooduc","gresca","yetvir","rufgro","pinwar","pinsis","amered","hoowar","merlin","redhea"]}